static_config_class/__init__.py
static_config_class/configuration.py
static_config_class/exceptions.py
static_config_class/py.typed
static_config_class-0.0.3.dist-info/LICENSE
static_config_class-0.0.3.dist-info/METADATA
static_config_class-0.0.3.dist-info/WHEEL
static_config_class-0.0.3.dist-info/top_level.txt
static_config_class-0.0.3.dist-info/RECORD
