Metadata-Version: 2.1
Name: static-config-class
Version: 0.0.3
Summary: Configuration manager for medium-sized projects (created for personal use)
Home-page: https://github.com/rlipperts/config
Author: Ruben Lipperts
Author-email: 
Classifier: Programming Language :: Python :: 3.9
Classifier: License :: OSI Approved :: MIT License
Classifier: Operating System :: OS Independent
Classifier: Topic :: System :: Installation/Setup
Requires-Python: ~=3.9
License-File: LICENSE
Requires-Dist: jsonschema
Provides-Extra: test
Requires-Dist: pytest ; extra == 'test'
Requires-Dist: flake8 ; extra == 'test'
Requires-Dist: pylint ; extra == 'test'
Requires-Dist: mypy ; extra == 'test'
